rbclassifydoc/__init__.py
rbclassifydoc/classify.py
rbpackage/__init__.py
rbpackage/classify.py
rbclassifydoc-0.2.0.dist-info/METADATA
rbclassifydoc-0.2.0.dist-info/WHEEL
rbclassifydoc-0.2.0.dist-info/top_level.txt
rbclassifydoc-0.2.0.dist-info/RECORD
